{
        "results":
        [
                {
                        "group":
                        {
                                "id":1,
                                "name":"General",
                                "created_at":"2011-01-28T16:30:41Z",
                                "updated_at":"2011-01-28T16:30:41Z"
                        }
                },
                {
                        "group":
                        {
                                "id":2,
                                "name":"Supervisor",
                                "created_at":"2011-01-28T16:30:42Z",
                                "updated_at":"2011-01-28T16:30:42Z"
                        }
                }
        ],
        "page":1,
        "count":20,
        "total":2
}